web_search_mcp/__init__.py
web_search_mcp/server.py
web_search_mcp-0.3.0.dist-info/METADATA
web_search_mcp-0.3.0.dist-info/WHEEL
web_search_mcp-0.3.0.dist-info/entry_points.txt
web_search_mcp-0.3.0.dist-info/RECORD
