Metadata-Version: 2.4
Name: web-search-mcp
Version: 0.3.0
Summary: 一个用于联网搜索的MCP Server.
Requires-Python: >=3.12
Requires-Dist: httpx>=0.28.1
Requires-Dist: mcp[cli]>=1.8.1
